{"name":"blog","postlist":[{"title":"hello-hexo","slug":"hello-hexo","date":"2016-02-17T10:03:20.000Z","updated":"2022-01-20T04:12:09.026Z","comments":true,"path":"api/articles/hello-hexo.json","excerpt":null,"keywords":null,"cover":null,"content":null,"raw":null,"categories":[{"name":"node","path":"api/categories/node.json"}],"tags":[{"name":"heox","path":"api/tags/heox.json"},{"name":"blog","path":"api/tags/blog.json"},{"name":"node","path":"api/tags/node.json"}]},{"title":"After hello hexo","slug":"hexo-theme","date":"2016-02-17T10:03:20.000Z","updated":"2022-01-20T04:12:09.026Z","comments":true,"path":"api/articles/hexo-theme.json","excerpt":null,"keywords":null,"cover":null,"content":null,"raw":null,"categories":[{"name":"node","path":"api/categories/node.json"}],"tags":[{"name":"heox","path":"api/tags/heox.json"},{"name":"blog","path":"api/tags/blog.json"},{"name":"node","path":"api/tags/node.json"}]}]}